CHANGES.rst
MANIFEST.in
README.rst
setup.cfg
setup.py
pyramid_royal.egg-info/PKG-INFO
pyramid_royal.egg-info/SOURCES.txt
pyramid_royal.egg-info/dependency_links.txt
pyramid_royal.egg-info/entry_points.txt
pyramid_royal.egg-info/pbr.json
pyramid_royal.egg-info/requires.txt
pyramid_royal.egg-info/top_level.txt
royal/__init__.py
royal/declarative.py
royal/deserializer.py
royal/directives.py
royal/exceptions.py
royal/interfaces.py
royal/presources.py
royal/renderer.py
royal/resource.py
royal/testing.py
royal/views.py
royal/ext/__init__.py
royal/ext/sqla.py
royal/tests/__init__.py
royal/tests/functional/__init__.py
royal/tests/functional/test_example.py
royal/tests/functional/test_presources.py
royal/tests/functional/test_sa_example.py
royal/tests/unittests/__init__.py
royal/tests/unittests/test_resources.py