Metadata-Version: 1.1
Name: pyramid-royal
Version: 0.8.10
Summary: 
Home-page: https://github.com/hadrien/pyramid_royal
Author: Hadrien David
Author-email: hadrien+pypi@ectobal.com
License: UNKNOWN
Keywords: web wsgi pylons pyramid REST traversal
Platform: UNKNOWN
Classifier: Development Status :: 3 - Alpha
Classifier: Environment :: Plugins
Classifier: Framework :: Pyramid
Classifier: Intended Audience :: Developers
Classifier: Programming Language :: Python
Classifier: Programming Language :: Python :: 2.7
Classifier: Programming Language :: Python :: Implementation :: CPython
Classifier: Topic :: Internet :: WWW/HTTP
Classifier: Topic :: Internet :: WWW/HTTP :: WSGI
